azure/iot/device/__init__.py
azure/iot/device/constant.py
azure/iot/device/custom_typing.py
azure/iot/device/exceptions.py
azure/iot/device/patch.py
azure/iot/device/patch_documentation.py
azure/iot/device/py.typed
azure/iot/device/user_agent.py
azure/iot/device/aio/__init__.py
azure/iot/device/aio/patch_documentation.py
azure/iot/device/common/__init__.py
azure/iot/device/common/alarm.py
azure/iot/device/common/async_adapter.py
azure/iot/device/common/evented_callback.py
azure/iot/device/common/handle_exceptions.py
azure/iot/device/common/http_transport.py
azure/iot/device/common/mqtt_transport.py
azure/iot/device/common/transport_exceptions.py
azure/iot/device/common/auth/__init__.py
azure/iot/device/common/auth/connection_string.py
azure/iot/device/common/auth/sastoken.py
azure/iot/device/common/auth/signing_mechanism.py
azure/iot/device/common/models/__init__.py
azure/iot/device/common/models/proxy_options.py
azure/iot/device/common/models/x509.py
azure/iot/device/common/pipeline/__init__.py
azure/iot/device/common/pipeline/config.py
azure/iot/device/common/pipeline/pipeline_events_base.py
azure/iot/device/common/pipeline/pipeline_events_mqtt.py
azure/iot/device/common/pipeline/pipeline_exceptions.py
azure/iot/device/common/pipeline/pipeline_nucleus.py
azure/iot/device/common/pipeline/pipeline_ops_base.py
azure/iot/device/common/pipeline/pipeline_ops_http.py
azure/iot/device/common/pipeline/pipeline_ops_mqtt.py
azure/iot/device/common/pipeline/pipeline_stages_base.py
azure/iot/device/common/pipeline/pipeline_stages_http.py
azure/iot/device/common/pipeline/pipeline_stages_mqtt.py
azure/iot/device/common/pipeline/pipeline_thread.py
azure/iot/device/iothub/__init__.py
azure/iot/device/iothub/abstract_clients.py
azure/iot/device/iothub/client_event.py
azure/iot/device/iothub/edge_hsm.py
azure/iot/device/iothub/inbox_manager.py
azure/iot/device/iothub/sync_clients.py
azure/iot/device/iothub/sync_handler_manager.py
azure/iot/device/iothub/sync_inbox.py
azure_iot_device-2.13.1.dist-info/LICENSE
azure_iot_device-2.13.1.dist-info/METADATA
azure_iot_device-2.13.1.dist-info/WHEEL
azure_iot_device-2.13.1.dist-info/top_level.txt
azure_iot_device-2.13.1.dist-info/RECORD
