Metadata-Version: 2.1
Name: azure-iot-device
Version: 2.13.1
Summary: Microsoft Azure IoT Device Library
Home-page: https://github.com/Azure/azure-iot-sdk-python/
Author: Microsoft Corporation
Author-email: opensource@microsoft.com
License: MIT License
Classifier: Development Status :: 5 - Production/Stable
Classifier: Intended Audience :: Developers
Classifier: Topic :: Software Development :: Libraries :: Python Modules
Classifier: License :: OSI Approved :: MIT License
Classifier: Programming Language :: Python
Classifier: Programming Language :: Python :: 3
Classifier: Programming Language :: Python :: 3.7
Classifier: Programming Language :: Python :: 3.8
Classifier: Programming Language :: Python :: 3.9
Classifier: Programming Language :: Python :: 3.10
Requires-Python: >=3.7, <4
License-File: LICENSE
Requires-Dist: urllib3 <1.27,>=1.26.5
Requires-Dist: deprecation <3.0.0,>=2.1.0
Requires-Dist: paho-mqtt <2.0.0,>=1.6.1
Requires-Dist: requests <2.32.0,>=2.20.0
Requires-Dist: requests-unixsocket <1.0.0,>=0.1.5
Requires-Dist: janus
Requires-Dist: PySocks
Requires-Dist: typing-extensions
